tests/__init__.py
tests/conftest.py
tests/test_cli.py
tests/test_cuda.py
tests/test_engine.py
tests/test_exports.py
tests/test_integrations.py
tests/test_python.py
tests/test_solutions.py
ultralytics/__init__.py
ultralytics/py.typed
ultralytics/assets/bus.jpg
ultralytics/assets/zidane.jpg
ultralytics/cfg/__init__.py
ultralytics/cfg/default.yaml
ultralytics/cfg/datasets/Argoverse.yaml
ultralytics/cfg/datasets/DOTAv1.5.yaml
ultralytics/cfg/datasets/DOTAv1.yaml
ultralytics/cfg/datasets/GlobalWheat2020.yaml
ultralytics/cfg/datasets/HomeObjects-3K.yaml
ultralytics/cfg/datasets/ImageNet.yaml
ultralytics/cfg/datasets/Objects365.yaml
ultralytics/cfg/datasets/SKU-110K.yaml
ultralytics/cfg/datasets/TT100K.yaml
ultralytics/cfg/datasets/VOC.yaml
ultralytics/cfg/datasets/VisDrone.yaml
ultralytics/cfg/datasets/african-wildlife.yaml
ultralytics/cfg/datasets/brain-tumor.yaml
ultralytics/cfg/datasets/carparts-seg.yaml
ultralytics/cfg/datasets/coco-pose.yaml
ultralytics/cfg/datasets/coco.yaml
ultralytics/cfg/datasets/coco128-seg.yaml
ultralytics/cfg/datasets/coco128.yaml
ultralytics/cfg/datasets/coco8-grayscale.yaml
ultralytics/cfg/datasets/coco8-multispectral.yaml
ultralytics/cfg/datasets/coco8-pose.yaml
ultralytics/cfg/datasets/coco8-seg.yaml
ultralytics/cfg/datasets/coco8.yaml
ultralytics/cfg/datasets/construction-ppe.yaml
ultralytics/cfg/datasets/crack-seg.yaml
ultralytics/cfg/datasets/dog-pose.yaml
ultralytics/cfg/datasets/dota8-multispectral.yaml
ultralytics/cfg/datasets/dota8.yaml
ultralytics/cfg/datasets/hand-keypoints.yaml
ultralytics/cfg/datasets/kitti.yaml
ultralytics/cfg/datasets/lvis.yaml
ultralytics/cfg/datasets/medical-pills.yaml
ultralytics/cfg/datasets/open-images-v7.yaml
ultralytics/cfg/datasets/package-seg.yaml
ultralytics/cfg/datasets/signature.yaml
ultralytics/cfg/datasets/tiger-pose.yaml
ultralytics/cfg/datasets/xView.yaml
ultralytics/cfg/models/11/yolo11-cls-resnet18.yaml
ultralytics/cfg/models/11/yolo11-cls.yaml
ultralytics/cfg/models/11/yolo11-obb.yaml
ultralytics_sam3_batch-8.3.252.post1.dist-info/licenses/LICENSE
ultralytics_sam3_batch-8.3.252.post1.dist-info/METADATA
ultralytics_sam3_batch-8.3.252.post1.dist-info/WHEEL
ultralytics_sam3_batch-8.3.252.post1.dist-info/entry_points.txt
ultralytics_sam3_batch-8.3.252.post1.dist-info/top_level.txt
ultralytics_sam3_batch-8.3.252.post1.dist-info/RECORD
